ndmg/__init__.py
ndmg/graph/__init__.py
ndmg/graph/gen_graph.py
ndmg/preproc/__init__.py
ndmg/preproc/preproc_anat.py
ndmg/preproc/rescale_bvec.py
ndmg/register/__init__.py
ndmg/register/gen_reg.py
ndmg/scripts/__init__.py
ndmg/scripts/multigraph_pipeline.py
ndmg/scripts/ndmg_bids.py
ndmg/scripts/ndmg_cloud.py
ndmg/scripts/ndmg_dwi_pipeline.py
ndmg/scripts/ndmg_setup.py
ndmg/stats/__init__.py
ndmg/stats/group_func.py
ndmg/stats/plotly_helper.py
ndmg/stats/qa_adjacency.py
ndmg/stats/qa_fibers.py
ndmg/stats/qa_graphs.py
ndmg/stats/qa_graphs_plotting.py
ndmg/stats/qa_mri.py
ndmg/stats/qa_reg.py
ndmg/stats/qa_tensor.py
ndmg/track/__init__.py
ndmg/track/gen_track.py
ndmg/utils/__init__.py
ndmg/utils/bids_utils.py
ndmg/utils/gen_utils.py
ndmg/utils/loadGraphs.py
ndmg/utils/mri_autoingest.py
ndmg/utils/nifti_to_binary.py
ndmg/utils/nifti_to_png.py
ndmg/utils/reg_utils.py
ndmg/utils/s3_utils.py
ndmg-0.2.1.dist-info/LICENSE.txt
ndmg-0.2.1.dist-info/METADATA
ndmg-0.2.1.dist-info/WHEEL
ndmg-0.2.1.dist-info/entry_points.txt
ndmg-0.2.1.dist-info/top_level.txt
ndmg-0.2.1.dist-info/RECORD
